LICENSE
README.md
setup.cfg
setup.py
micloud/__init__.py
micloud/cli.py
micloud/micloud.py
micloud/micloudexception.py
micloud/miutils.py
micloud.egg-info/PKG-INFO
micloud.egg-info/SOURCES.txt
micloud.egg-info/dependency_links.txt
micloud.egg-info/entry_points.txt
micloud.egg-info/requires.txt
micloud.egg-info/top_level.txt