Metadata-Version: 2.1
Name: micloud
Version: 0.4
Summary: Xiaomi cloud connect library
Home-page: https://github.com/squachen/micloud
Author: Sammy Svensson
Author-email: sammy@ssvensson.se
License: MIT
Download-URL: https://github.com/Squachen/micloud/archive/v_0.4.tar.gz
Platform: UNKNOWN
License-File: LICENSE
